{"files":{"apps/web/.next/server/app/book-lesson/page_client-reference-manifest.js":{"size":20132,"mtime_nanos":1784207314191065800,"mode":420,"is_dir":false},"apps/web/.next/server/app/vocabulary.meta":{"size":190,"mtime_nanos":1784218153561476600,"mode":420,"is_dir":false},"apps/web/.next/server/edge-runtime-webpack.js.map":{"size":6132,"mtime_nanos":1784207294799323800,"mode":420,"is_dir":false},"apps/web/.next/server/app/tutor/availability/page.js":{"size":24211,"mtime_nanos":1784207290828897100,"mode":420,"is_dir":false},"apps/web/.next/server/pages/_app.js.nft.json":{"size":936,"mtime_nanos":1784277913834057600,"mode":420,"is_dir":false},"apps/web/.next/server/app/invite/accept/page.js.nft.json":{"size":10111,"mtime_nanos":1784277913771607100,"mode":420,"is_dir":false},"apps/web/.next/static/chunks/app":{"size":0,"mtime_nanos":0,"mode":0,"is_dir":true},"apps/web/.next/static/chunks/app/classroom":{"size":0,"mtime_nanos":0,"mode":0,"is_dir":true},"apps/web/.next/static/chunks/app/register/page-6da29e7306a1042e.js":{"size":10823,"mtime_nanos":1784207314128095100,"mode":420,"is_dir":false},"apps/web/.next/types/app/become-teacher/page.ts":{"size":3780,"mtime_nanos":1784207290851895500,"mode":420,"is_dir":false},"apps/web/.next/server/app/admin/teachers":{"size":0,"mtime_nanos":0,"mode":0,"is_dir":true},"apps/web/.next/server/app/student/profile":{"size":0,"mtime_nanos":0,"mode":0,"is_dir":true},"apps/web/.next/static/chunks/7628.de6487a09aba5d83.js":{"size":5445,"mtime_nanos":1784207314142636300,"mode":420,"is_dir":false},"apps/web/.next/server/app/forgot-password.html":{"size":13682,"mtime_nanos":1784218156489179900,"mode":420,"is_dir":false},"apps/web/.next/types/app":{"size":0,"mtime_nanos":0,"mode":0,"is_dir":true},"apps/web/.next/server/app/tutor/lessons.rsc":{"size":6303,"mtime_nanos":1784218153561476600,"mode":420,"is_dir":false},"apps/web/.next/static/chunks/2790-b69afaa8b092dc71.js":{"size":15805,"mtime_nanos":1784207314155149900,"mode":420,"is_dir":false},"apps/web/.next/types/app/auth/callback/page.ts":{"size":3783,"mtime_nanos":1784207290852938100,"mode":420,"is_dir":false},"apps/web/.next/server":{"size":0,"mtime_nanos":0,"mode":0,"is_dir":true},"apps/web/.next/static/chunks/app/forgot-password/page-c8f9cf76c0362b01.js":{"size":3336,"mtime_nanos":1784207314125739600,"mode":420,"is_dir":false},"apps/web/.next/server/app/student/wallet/page.js":{"size":33574,"mtime_nanos":1784207290828897100,"mode":420,"is_dir":false},"apps/web/.next/server/app/admin.rsc":{"size":5961,"mtime_nanos":1784218154859006900,"mode":420,"is_dir":false},"apps/web/.next/static/chunks/app/admin":{"size":0,"mtime_nanos":0,"mode":0,"is_dir":true},"apps/web/.next/static/chunks/app/login/page-d873f30c2be18a89.js":{"size":10563,"mtime_nanos":1784207314126736300,"mode":420,"is_dir":false},"apps/web/.next/server/app/terms":{"size":0,"mtime_nanos":0,"mode":0,"is_dir":true},"apps/web/.next/server/app/student/lessons/page.js":{"size":21290,"mtime_nanos":1784207290827806900,"mode":420,"is_dir":false},"apps/web/.next/static/chunks/app/classroom/[roomId]":{"size":0,"mtime_nanos":0,"mode":0,"is_dir":true},"apps/web/.next/server/app/student/discover.meta":{"size":229,"mtime_nanos":1784218157408914600,"mode":420,"is_dir":false},"apps/web/.next/types/app/courses":{"size":0,"mtime_nanos":0,"mode":0,"is_dir":true},"apps/web/.next/types/app/courses/[id]":{"size":0,"mtime_nanos":0,"mode":0,"is_dir":true},"apps/web/.next/types/app/invite":{"size":0,"mtime_nanos":0,"mode":0,"is_dir":true},"apps/web/.next/diagnostics/build-diagnostics.json":{"size":93,"mtime_nanos":1784207345676542000,"mode":420,"is_dir":false},"apps/web/.next/static/chunks/app/layout-afa5e9c4e0dde710.js":{"size":24675,"mtime_nanos":1784207314119811000,"mode":420,"is_dir":false},"apps/web/.next/static/chunks/app/admin/payouts":{"size":0,"mtime_nanos":0,"mode":0,"is_dir":true},"apps/web/.next/server/app/privacy.rsc":{"size":5921,"mtime_nanos":1784218157408914600,"mode":420,"is_dir":false},"apps/web/.next/types/app/privacy":{"size":0,"mtime_nanos":0,"mode":0,"is_dir":true},"apps/web/.next/server/pages":{"size":0,"mtime_nanos":0,"mode":0,"is_dir":true},"apps/web/.next/server/app/forgot-password.rsc":{"size":5953,"mtime_nanos":1784218156489179900,"mode":420,"is_dir":false},"apps/web/.next/server/app/tutor/earnings":{"size":0,"mtime_nanos":0,"mode":0,"is_dir":true},"apps/web/.next/server/app/_not-found/page.js.nft.json":{"size":9924,"mtime_nanos":1784277913771607100,"mode":420,"is_dir":false},"apps/web/.next/types/app/book-lesson/page.ts":{"size":3771,"mtime_nanos":1784207290857956900,"mode":420,"is_dir":false},"apps/web/.next/server/app/_not-found.rsc":{"size":5564,"mtime_nanos":1784218156489179900,"mode":420,"is_dir":false},"apps/web/.next/server/webpack-runtime.js":{"size":1486,"mtime_nanos":1784207290835612200,"mode":420,"is_dir":false},"apps/web/.next/static/chunks/app/auth/callback":{"size":0,"mtime_nanos":0,"mode":0,"is_dir":true},"apps/web/.next/static/chunks/app/tutor/profile":{"size":0,"mtime_nanos":0,"mode":0,"is_dir":true},"apps/web/.next/server/app/help/page.js":{"size":27583,"mtime_nanos":1784207290822605300,"mode":420,"is_dir":false},"apps/web/.next/static/chunks/app/tutor/availability":{"size":0,"mtime_nanos":0,"mode":0,"is_dir":true},"apps/web/.next/static/chunks/app/_not-found":{"size":0,"mtime_nanos":0,"mode":0,"is_dir":true},"apps/web/.next/types/app/student/page.ts":{"size":3759,"mtime_nanos":1784207290861009700,"mode":420,"is_dir":false},"apps/web/.next/types/app/admin/teachers/page.ts":{"size":3786,"mtime_nanos":1784207290852938100,"mode":420,"is_dir":false},"apps/web/.next/types/app/student":{"size":0,"mtime_nanos":0,"mode":0,"is_dir":true},"apps/web/.next/types/app/tutors/[id]":{"size":0,"mtime_nanos":0,"mode":0,"is_dir":true},"apps/web/.next/BUILD_ID":{"size":21,"mtime_nanos":1784207345614055500,"mode":420,"is_dir":false},"apps/web/.next/server/app/teacher-training/page.js.nft.json":{"size":9991,"mtime_nanos":1784277913771607100,"mode":420,"is_dir":false},"apps/web/.next/server/app/en.rsc":{"size":5891,"mtime_nanos":1784218154874627300,"mode":420,"is_dir":false},"apps/web/.next/server/app/auth/callback/page.js.nft.json":{"size":10086,"mtime_nanos":1784277913771607100,"mode":420,"is_dir":false},"apps/web/.next/server/app/_not-found.html":{"size":10370,"mtime_nanos":1784218156489179900,"mode":420,"is_dir":false},"apps/web/.next/server/app/help":{"size":0,"mtime_nanos":0,"mode":0,"is_dir":true},"apps/web/.next/server/next-font-manifest.js":{"size":106,"mtime_nanos":1784207314097513600,"mode":420,"is_dir":false},"apps/web/.next/server/pages-manifest.json":{"size":128,"mtime_nanos":1784218162281496000,"mode":420,"is_dir":false},"apps/web/.next/static/chunks/app/tutor/earnings/page-34b60f242fbab6ad.js":{"size":18671,"mtime_nanos":1784207314137551000,"mode":420,"is_dir":false},"apps/web/.next/types/app/invite/accept":{"size":0,"mtime_nanos":0,"mode":0,"is_dir":true},"apps/web/.next/types/app/admin/payouts":{"size":0,"mtime_nanos":0,"mode":0,"is_dir":true},"apps/web/.next/types/app/classroom":{"size":0,"mtime_nanos":0,"mode":0,"is_dir":true},"apps/web/.next/server/app/student/lessons.html":{"size":10818,"mtime_nanos":1784218157408914600,"mode":420,"is_dir":false},"apps/web/.next/types/app/teacher-training/page.ts":{"size":3786,"mtime_nanos":1784207290855962200,"mode":420,"is_dir":false},"apps/web/.next/server/app/login/page.js":{"size":24364,"mtime_nanos":1784207290824600100,"mode":420,"is_dir":false},"apps/web/.next/server/app/register.meta":{"size":184,"mtime_nanos":1784218157408914600,"mode":420,"is_dir":false},"apps/web/.next/static/chunks/1530-21e3e33019716615.js":{"size":47194,"mtime_nanos":1784207314148504100,"mode":420,"is_dir":false},"apps/web/.next/images-manifest.json":{"size":2608,"mtime_nanos":1784218162714207100,"mode":420,"is_dir":false},"apps/web/.next/server/app/_not-found":{"size":0,"mtime_nanos":0,"mode":0,"is_dir":true},"apps/web/.next/types/app/admin/payouts/page.ts":{"size":3783,"mtime_nanos":1784207290852938100,"mode":420,"is_dir":false},"apps/web/.next/server/app/become-teacher/page.js":{"size":30316,"mtime_nanos":1784207290821561600,"mode":420,"is_dir":false},"apps/web/.next/server/app/tutor/profile/page.js":{"size":16305,"mtime_nanos":1784207290828804200,"mode":420,"is_dir":false},"apps/web/.next/server/app/faq":{"size":0,"mtime_nanos":0,"mode":0,"is_dir":true},"apps/web/.next/server/app/tutor.meta":{"size":175,"mtime_nanos":1784218154874627300,"mode":420,"is_dir":false},"apps/web/.next/static/chunks/app/become-teacher/page-babf3191a17502ba.js":{"size":19985,"mtime_nanos":1784207314122074200,"mode":420,"is_dir":false},"apps/web/.next/static/css/e34b5a27d547b7a3.css":{"size":59355,"mtime_nanos":1784207314145395000,"mode":420,"is_dir":false},"apps/web/.next/server/app/teacher-training/page_client-reference-manifest.js":{"size":20195,"mtime_nanos":1784207314186874600,"mode":420,"is_dir":false},"apps/web/.next/server/chunks/3735.js":{"size":127935,"mtime_nanos":1784207290834615900,"mode":420,"is_dir":false},"apps/web/.next/static/chunks/app/courses/page-e6d8beaf05128792.js":{"size":10927,"mtime_nanos":1784207314124742500,"mode":420,"is_dir":false},"apps/web/.next/types/app/tutor/availability":{"size":0,"mtime_nanos":0,"mode":0,"is_dir":true},"apps/web/.next/server/app/become-teacher.html":{"size":12160,"mtime_nanos":1784218153545855200,"mode":420,"is_dir":false},"apps/web/.next/types/app/en":{"size":0,"mtime_nanos":0,"mode":0,"is_dir":true},"apps/web/.next/server/app/en/page_client-reference-manifest.js":{"size":20057,"mtime_nanos":1784207314191065800,"mode":420,"is_dir":false},"apps/web/.next/types/app/tutor/availability/page.ts":{"size":3798,"mtime_nanos":1784207290857956900,"mode":420,"is_dir":false},"apps/web/.next/types/app/help":{"size":0,"mtime_nanos":0,"mode":0,"is_dir":true},"apps/web/.next/server/app/favicon.ico":{"size":0,"mtime_nanos":0,"mode":0,"is_dir":true},"apps/web/.next/app-path-routes-manifest.json":{"size":1384,"mtime_nanos":1784207342962148700,"mode":420,"is_dir":false},"apps/web/.next/server/app/admin/teachers/page.js":{"size":29759,"mtime_nanos":1784207290821419600,"mode":420,"is_dir":false},"apps/web/.next/static/chunks/app/forgot-password":{"size":0,"mtime_nanos":0,"mode":0,"is_dir":true},"apps/web/.next/types/app/admin":{"size":0,"mtime_nanos":0,"mode":0,"is_dir":true},"apps/web/.next/server/app/student/page.js":{"size":86715,"mtime_nanos":1784207290834615900,"mode":420,"is_dir":false},"apps/web/.next/server/app/tutor/profile/page_client-reference-manifest.js":{"size":20725,"mtime_nanos":1784207314188987300,"mode":420,"is_dir":false},"apps/web/.next/server/app/tutor/lessons.meta":{"size":218,"mtime_nanos":1784218153561476600,"mode":420,"is_dir":false},"apps/web/.next/server/app/tutor/profile.rsc":{"size":6382,"mtime_nanos":1784218154859006900,"mode":420,"is_dir":false},"apps/web/.next/server/app/auth/callback.rsc":{"size":6207,"mtime_nanos":1784218157408914600,"mode":420,"is_dir":false},"apps/web/.next/server/app/faq/page.js.nft.json":{"size":9969,"mtime_nanos":1784277913771607100,"mode":420,"is_dir":false},"apps/web/.next/server/app/reset-password.rsc":{"size":5949,"mtime_nanos":1784218157408914600,"mode":420,"is_dir":false},"apps/web/.next/server/app/tutor/earnings/page.js.nft.json":{"size":10137,"mtime_nanos":1784277913771607100,"mode":420,"is_dir":false},"apps/web/.next/server/interception-route-rewrite-manifest.js":{"size":48,"mtime_nanos":1784207294798268200,"mode":420,"is_dir":false},"apps/web/.next/server/app/student/profile.meta":{"size":226,"mtime_nanos":1784218157705722200,"mode":420,"is_dir":false},"apps/web/.next/server/app/vocabulary":{"size":0,"mtime_nanos":0,"mode":0,"is_dir":true},"apps/web/.next/server/app/become-teacher/page_client-reference-manifest.js":{"size":20093,"mtime_nanos":1784207314158195100,"mode":420,"is_dir":false},"apps/web/.next/server/app/privacy":{"size":0,"mtime_nanos":0,"mode":0,"is_dir":true},"apps/web/.next/static/chunks/app/tutor/profile/page-5d8185e9e81c0962.js":{"size":159,"mtime_nanos":1784207314137551000,"mode":420,"is_dir":false},"apps/web/.next/server/app/tutor/lessons":{"size":0,"mtime_nanos":0,"mode":0,"is_dir":true},"apps/web/.next/server/app/admin/payouts.meta":{"size":218,"mtime_nanos":1784218156489179900,"mode":420,"is_dir":false},"apps/web/.next/types/app/privacy/page.ts":{"size":3759,"mtime_nanos":1784207290851895500,"mode":420,"is_dir":false},"apps/web/.next/server/app/tutor/profile/page.js.nft.json":{"size":10281,"mtime_nanos":1784277913787193900,"mode":420,"is_dir":false},"apps/web/.next/server/app/privacy.html":{"size":19791,"mtime_nanos":1784218157408914600,"mode":420,"is_dir":false},"apps/web/.next/server/app/reset-password":{"size":0,"mtime_nanos":0,"mode":0,"is_dir":true},"apps/web/.next/server/app/admin/articles.rsc":{"size":6403,"mtime_nanos":1784218154874627300,"mode":420,"is_dir":false},"apps/web/.next/types/app/tutor/earnings/page.ts":{"size":3786,"mtime_nanos":1784207290857956900,"mode":420,"is_dir":false},"apps/web/.next/server/app/auth/callback/page.js":{"size":19789,"mtime_nanos":1784207290821561600,"mode":420,"is_dir":false},"apps/web/.next/server/app/student/discover/page.js":{"size":33387,"mtime_nanos":1784207290827806900,"mode":420,"is_dir":false},"apps/web/.next/server/app/book-lesson.meta":{"size":193,"mtime_nanos":1784218153561476600,"mode":420,"is_dir":false},"apps/web/.next/server/pages/_error.js.nft.json":{"size":10223,"mtime_nanos":1784277913834057600,"mode":420,"is_dir":false},"apps/web/.next/server/app/admin":{"size":0,"mtime_nanos":0,"mode":0,"is_dir":true},"apps/web/.next/server/app/admin/page_client-reference-manifest.js":{"size":20114,"mtime_nanos":1784207314191065800,"mode":420,"is_dir":false},"apps/web/.next/server/app/courses/[id]/page.js.nft.json":{"size":10189,"mtime_nanos":1784277913771607100,"mode":420,"is_dir":false},"apps/web/.next/static/SCGubTP48JQlyBvub_uJC/_ssgManifest.js":{"size":80,"mtime_nanos":1784218162613963400,"mode":420,"is_dir":false},"apps/web/.next/static/chunks/app/admin/articles":{"size":0,"mtime_nanos":0,"mode":0,"is_dir":true},"apps/web/.next/server/app/vocabulary/page.js.nft.json":{"size":9992,"mtime_nanos":1784277913771607100,"mode":420,"is_dir":false},"apps/web/.next/server/app/favicon.ico.body":{"size":25931,"mtime_nanos":1784218155171356300,"mode":420,"is_dir":false},"apps/web/.next/server/app/forgot-password/page.js.nft.json":{"size":9969,"mtime_nanos":1784277913771607100,"mode":420,"is_dir":false},"apps/web/.next/types/app/student/discover":{"size":0,"mtime_nanos":0,"mode":0,"is_dir":true},"apps/web/.next/types/app/help/page.ts":{"size":3750,"mtime_nanos":1784207290851895500,"mode":420,"is_dir":false},"apps/web/.next/server/app/student/discover/page.js.nft.json":{"size":10137,"mtime_nanos":1784277913771607100,"mode":420,"is_dir":false},"apps/web/.next/server/app/forgot-password":{"size":0,"mtime_nanos":0,"mode":0,"is_dir":true},"apps/web/.next/server/app/en":{"size":0,"mtime_nanos":0,"mode":0,"is_dir":true},"apps/web/.next/types/app/admin/articles/page.ts":{"size":3786,"mtime_nanos":1784207290852938100,"mode":420,"is_dir":false},"apps/web/.next/server/app/student/lessons/page_client-reference-manifest.js":{"size":20591,"mtime_nanos":1784207314186874600,"mode":420,"is_dir":false},"apps/web/.next/static/chunks/pages":{"size":0,"mtime_nanos":0,"mode":0,"is_dir":true},"apps/web/.next/server/middleware-build-manifest.js":{"size":922,"mtime_nanos":1784207314097513600,"mode":420,"is_dir":false},"apps/web/.next/server/app/help.rsc":{"size":5898,"mtime_nanos":1784218157393294500,"mode":420,"is_dir":false},"apps/web/.next/server/app/student/lessons/page.js.nft.json":{"size":10137,"mtime_nanos":1784277913771607100,"mode":420,"is_dir":false},"apps/web/.next/static/chunks/app/faq/page-37e353b20b648d6e.js":{"size":11296,"mtime_nanos":1784207314125739600,"mode":420,"is_dir":false},"apps/web/.next/server/app/student/discover.rsc":{"size":6361,"mtime_nanos":1784218157408914600,"mode":420,"is_dir":false},"apps/web/.next/types/app/admin/teachers":{"size":0,"mtime_nanos":0,"mode":0,"is_dir":true},"apps/web/.next/static/chunks/app/tutor/lessons/page-05f203a5f76c1f44.js":{"size":12562,"mtime_nanos":1784207314137551000,"mode":420,"is_dir":false},"apps/web/.next/server/app/become-teacher.rsc":{"size":5949,"mtime_nanos":1784218153545855200,"mode":420,"is_dir":false},"apps/web/.next/server/app/page.js.nft.json":{"size":9841,"mtime_nanos":1784277913771607100,"mode":420,"is_dir":false},"apps/web/.next/static/chunks/framework-d89a50f3a2bac6a1.js":{"size":182717,"mtime_nanos":1784207314145395000,"mode":420,"is_dir":false},"apps/web/.next/server/app/tutor/lessons/page.js.nft.json":{"size":10112,"mtime_nanos":1784277913771607100,"mode":420,"is_dir":false},"apps/web/.next/server/app":{"size":0,"mtime_nanos":0,"mode":0,"is_dir":true},"apps/web/.next/server/app/student/profile/page.js":{"size":16321,"mtime_nanos":1784207290828897100,"mode":420,"is_dir":false},"apps/web/.next/static/chunks/app/book-lesson":{"size":0,"mtime_nanos":0,"mode":0,"is_dir":true},"apps/web/.next/server/src/middleware.js":{"size":105142,"mtime_nanos":1784207294800321600,"mode":420,"is_dir":false},"apps/web/.next/server/chunks/853.js":{"size":9802,"mtime_nanos":1784207290838229200,"mode":420,"is_dir":false},"apps/web/.next/static/chunks/app/tutor/lessons":{"size":0,"mtime_nanos":0,"mode":0,"is_dir":true},"apps/web/.next/types/app/register":{"size":0,"mtime_nanos":0,"mode":0,"is_dir":true},"apps/web/.next/server/app/tutor/earnings.rsc":{"size":6355,"mtime_nanos":1784218153561476600,"mode":420,"is_dir":false},"apps/web/.next/server/app/tutors/[id]/page.js":{"size":40883,"mtime_nanos":1784207290832886500,"mode":420,"is_dir":false},"apps/web/.next/static/chunks/app/reset-password/page-05d1a44a517cddcd.js":{"size":4551,"mtime_nanos":1784207314128095100,"mode":420,"is_dir":false},"apps/web/.next/server/app/tutor/earnings/page.js":{"size":29616,"mtime_nanos":1784207290828897100,"mode":420,"is_dir":false},"apps/web/.next/server/app/tutor/availability/page.js.nft.json":{"size":10137,"mtime_nanos":1784277913771607100,"mode":420,"is_dir":false},"apps/web/.next/types/app/student/wallet":{"size":0,"mtime_nanos":0,"mode":0,"is_dir":true},"apps/web/.next/server/app/tutor/page.js.nft.json":{"size":9992,"mtime_nanos":1784277913787193900,"mode":420,"is_dir":false},"apps/web/.next/server/app/classroom/[roomId]/page.js":{"size":152915,"mtime_nanos":1784207290838229200,"mode":420,"is_dir":false},"apps/web/.next/static/chunks/app/invite":{"size":0,"mtime_nanos":0,"mode":0,"is_dir":true},"apps/web/.next/server/chunks/7842.js":{"size":8859,"mtime_nanos":1784207290834615900,"mode":420,"is_dir":false},"apps/web/.next/server/app/tutor/availability.rsc":{"size":6370,"mtime_nanos":1784218153545855200,"mode":420,"is_dir":false},"apps/web/.next/static/chunks/app/courses/[id]":{"size":0,"mtime_nanos":0,"mode":0,"is_dir":true},"apps/web/.next/server/app/student/profile/page_client-reference-manifest.js":{"size":20735,"mtime_nanos":1784207314186874600,"mode":420,"is_dir":false},"apps/web/.next/static/chunks/app/classroom/[roomId]/page-830b72951f467b42.js":{"size":42635,"mtime_nanos":1784207314146508600,"mode":420,"is_dir":false},"apps/web/.next/types/app/admin/articles":{"size":0,"mtime_nanos":0,"mode":0,"is_dir":true},"apps/web/.next/server/app/favicon.ico/route.js":{"size":72617,"mtime_nanos":1784207290820422000,"mode":420,"is_dir":false},"apps/web/.next/required-server-files.json":{"size":10267,"mtime_nanos":1784207345629679500,"mode":420,"is_dir":false},"apps/web/.next/server/pages/500.html":{"size":2007,"mtime_nanos":1784218156411073200,"mode":420,"is_dir":false},"apps/web/.next/server/app/index.meta":{"size":145,"mtime_nanos":1784218154874627300,"mode":420,"is_dir":false},"apps/web/.next/types/app/tutor/page.ts":{"size":3753,"mtime_nanos":1784207290861009700,"mode":420,"is_dir":false},"apps/web/.next/server/app/faq/page_client-reference-manifest.js":{"size":20060,"mtime_nanos":1784207314183730800,"mode":420,"is_dir":false},"apps/web/.next/static/chunks/app/student":{"size":0,"mtime_nanos":0,"mode":0,"is_dir":true},"apps/web/.next/server/app/faq/page.js":{"size":28187,"mtime_nanos":1784207290821561600,"mode":420,"is_dir":false},"apps/web/.next/server/app/admin/articles/page_client-reference-manifest.js":{"size":20536,"mtime_nanos":1784207314155149900,"mode":420,"is_dir":false},"apps/web/.next/types/app/tutor/lessons":{"size":0,"mtime_nanos":0,"mode":0,"is_dir":true},"apps/web/.next/server/app/login.rsc":{"size":5961,"mtime_nanos":1784218156489179900,"mode":420,"is_dir":false},"apps/web/.next/static/chunks/8883-57748f83d541529e.js":{"size":96035,"mtime_nanos":1784207314148504100,"mode":420,"is_dir":false},"apps/web/.next/server/app/auth":{"size":0,"mtime_nanos":0,"mode":0,"is_dir":true},"apps/web/.next/server/app/invite":{"size":0,"mtime_nanos":0,"mode":0,"is_dir":true},"apps/web/.next/server/app/terms/page.js.nft.json":{"size":9969,"mtime_nanos":1784277913771607100,"mode":420,"is_dir":false},"apps/web/.next/server/app/classroom/[roomId]/page_client-reference-manifest.js":{"size":20158,"mtime_nanos":1784207314191065800,"mode":420,"is_dir":false},"apps/web/.next/types/app/reset-password":{"size":0,"mtime_nanos":0,"mode":0,"is_dir":true},"apps/web/.next/server/app/tutors/[id]/page_client-reference-manifest.js":{"size":20876,"mtime_nanos":1784207314190068400,"mode":420,"is_dir":false},"apps/web/.next/static/chunks/5695-d695ed8825add7dd.js":{"size":14963,"mtime_nanos":1784207314154152500,"mode":420,"is_dir":false},"apps/web/.next/server/app/terms.html":{"size":19719,"mtime_nanos":1784218153545855200,"mode":420,"is_dir":false},"apps/web/.next/server/app/login.meta":{"size":175,"mtime_nanos":1784218156489179900,"mode":420,"is_dir":false},"apps/web/.next/server/app/reset-password/page.js.nft.json":{"size":9969,"mtime_nanos":1784277913771607100,"mode":420,"is_dir":false},"apps/web/.next/static/chunks/app/book-lesson/page-4feca50565b8f664.js":{"size":30144,"mtime_nanos":1784207314141637500,"mode":420,"is_dir":false},"apps/web/.next/static/chunks/app/privacy":{"size":0,"mtime_nanos":0,"mode":0,"is_dir":true},"apps/web/.next/server/app/admin/articles.meta":{"size":221,"mtime_nanos":1784218154874627300,"mode":420,"is_dir":false},"apps/web/.next/static/chunks/app/tutor/availability/page-98746f615833b1be.js":{"size":12247,"mtime_nanos":1784207314137551000,"mode":420,"is_dir":false},"apps/web/.next/routes-manifest.json":{"size":7232,"mtime_nanos":1784218162390846500,"mode":420,"is_dir":false},"apps/web/.next/server/app/register/page_client-reference-manifest.js":{"size":20123,"mtime_nanos":1784207314185867900,"mode":420,"is_dir":false},"apps/web/.next/static/chunks/app/privacy/page-09b2956fcd336986.js":{"size":11083,"mtime_nanos":1784207314126736300,"mode":420,"is_dir":false},"apps/web/.next/types/app/tutors":{"size":0,"mtime_nanos":0,"mode":0,"is_dir":true},"apps/web/.next/types/app/student/lessons/page.ts":{"size":3789,"mtime_nanos":1784207290856959900,"mode":420,"is_dir":false},"apps/web/.next/server/app/tutor/lessons/page.js":{"size":23525,"mtime_nanos":1784207290827806900,"mode":420,"is_dir":false},"apps/web/.next/static/chunks":{"size":0,"mtime_nanos":0,"mode":0,"is_dir":true},"apps/web/.next/types/app/faq/page.ts":{"size":3747,"mtime_nanos":1784207290851895500,"mode":420,"is_dir":false},"apps/web/.next/server/app/tutor/profile":{"size":0,"mtime_nanos":0,"mode":0,"is_dir":true},"apps/web/.next/server/app/courses":{"size":0,"mtime_nanos":0,"mode":0,"is_dir":true},"apps/web/.next/static/chunks/app/vocabulary":{"size":0,"mtime_nanos":0,"mode":0,"is_dir":true},"apps/web/.next/static/chunks/5070-e95f686c39c4cca0.js":{"size":72665,"mtime_nanos":1784207314146508600,"mode":420,"is_dir":false},"apps/web/.next/server/app/admin.html":{"size":26924,"mtime_nanos":1784218154859006900,"mode":420,"is_dir":false},"apps/web/.next/types/app/register/page.ts":{"size":3762,"mtime_nanos":1784207290853935500,"mode":420,"is_dir":false},"apps/web/.next/server/app/classroom/[roomId]/page.js.nft.json":{"size":10112,"mtime_nanos":1784277913771607100,"mode":420,"is_dir":false},"apps/web/.next/server/app/admin/teachers/page_client-reference-manifest.js":{"size":20488,"mtime_nanos":1784207314155149900,"mode":420,"is_dir":false},"apps/web/.next/static/chunks/main-app-4c5c8b63f655479c.js":{"size":561,"mtime_nanos":1784207314107237500,"mode":420,"is_dir":false},"apps/web/.next/server/app/register/page.js":{"size":24753,"mtime_nanos":1784207290826595200,"mode":420,"is_dir":false},"apps/web/.next/server/app/invite/accept":{"size":0,"mtime_nanos":0,"mode":0,"is_dir":true},"apps/web/.next/server/app/vocabulary.rsc":{"size":6029,"mtime_nanos":1784218153561476600,"mode":420,"is_dir":false},"apps/web/.next/server/app/courses/page.js.nft.json":{"size":10015,"mtime_nanos":1784277913771607100,"mode":420,"is_dir":false},"apps/web/.next/static/chunks/3809.45b47c674c9d395c.js":{"size":741,"mtime_nanos":1784207314145395000,"mode":420,"is_dir":false},"apps/web/.next/server/app/help.meta":{"size":172,"mtime_nanos":1784218157408914600,"mode":420,"is_dir":false},"apps/web/.next/server/app/terms.meta":{"size":175,"mtime_nanos":1784218153545855200,"mode":420,"is_dir":false},"apps/web/.next/static/chunks/app/help/page-be24dfe6cefbf80a.js":{"size":10682,"mtime_nanos":1784207314126736300,"mode":420,"is_dir":false},"apps/web/.next/server/app/book-lesson.html":{"size":10503,"mtime_nanos":1784218153561476600,"mode":420,"is_dir":false},"apps/web/.next/server/app/index.html":{"size":31668,"mtime_nanos":1784218154874627300,"mode":420,"is_dir":false},"apps/web/.next/server/app/index.rsc":{"size":5638,"mtime_nanos":1784218154874627300,"mode":420,"is_dir":false},"apps/web/.next/server/app/tutor/page_client-reference-manifest.js":{"size":20210,"mtime_nanos":1784207314191065800,"mode":420,"is_dir":false},"apps/web/.next/server/app/student/lessons.meta":{"size":226,"mtime_nanos":1784218157408914600,"mode":420,"is_dir":false},"apps/web/.next/server/app/student/wallet.meta":{"size":223,"mtime_nanos":1784218157487021000,"mode":420,"is_dir":false},"apps/web/.next/server/app/student.meta":{"size":181,"mtime_nanos":1784218154874627300,"mode":420,"is_dir":false},"apps/web/.next/server/app/book-lesson.rsc":{"size":5985,"mtime_nanos":1784218153561476600,"mode":420,"is_dir":false},"apps/web/.next/server/app/_not-found/page.js":{"size":15695,"mtime_nanos":1784207290821419600,"mode":420,"is_dir":false},"apps/web/.next/server/app/courses/page_client-reference-manifest.js":{"size":20216,"mtime_nanos":1784207314162189100,"mode":420,"is_dir":false},"apps/web/.next/static/chunks/app/vocabulary/page-fe378d833b74df85.js":{"size":12114,"mtime_nanos":1784207314136144500,"mode":420,"is_dir":false},"apps/web/.next/server/functions-config-manifest.json":{"size":37,"mtime_nanos":1784207345582845000,"mode":420,"is_dir":false},"apps/web/.next/static/chunks/2df137e7-44c7df29a0367194.js":{"size":173018,"mtime_nanos":1784207314146508600,"mode":420,"is_dir":false},"apps/web/.next/static/chunks/app/register":{"size":0,"mtime_nanos":0,"mode":0,"is_dir":true},"apps/web/.next/server/app/tutor/profile.meta":{"size":218,"mtime_nanos":1784218154859006900,"mode":420,"is_dir":false},"apps/web/.next/server/app/courses.meta":{"size":181,"mtime_nanos":1784218156489179900,"mode":420,"is_dir":false},"apps/web/.next/server/app/admin/teachers.html":{"size":11111,"mtime_nanos":1784218154874627300,"mode":420,"is_dir":false},"apps/web/.next/server/app/_not-found/page_client-reference-manifest.js":{"size":19875,"mtime_nanos":1784207314155149900,"mode":420,"is_dir":false},"apps/web/.next/server/app/tutor.html":{"size":10592,"mtime_nanos":1784218154874627300,"mode":420,"is_dir":false},"apps/web/.next/server/chunks/6857.js":{"size":549240,"mtime_nanos":1784207290834615900,"mode":420,"is_dir":false},"apps/web/.next/static/chunks/app/reset-password":{"size":0,"mtime_nanos":0,"mode":0,"is_dir":true},"apps/web/.next/server/app/favicon.ico/route.js.nft.json":{"size":9717,"mtime_nanos":1784277913771607100,"mode":420,"is_dir":false},"apps/web/.next/server/app/admin/articles/page.js":{"size":25851,"mtime_nanos":1784207290823603200,"mode":420,"is_dir":false},"apps/web/.next/server/app/student/lessons.rsc":{"size":6359,"mtime_nanos":1784218157408914600,"mode":420,"is_dir":false},"apps/web/.next/server/app/invite/accept/page_client-reference-manifest.js":{"size":20043,"mtime_nanos":1784207314185482400,"mode":420,"is_dir":false},"apps/web/.next/server/app/vocabulary.html":{"size":13091,"mtime_nanos":1784218153561476600,"mode":420,"is_dir":false},"apps/web/.next/server/app/classroom/[roomId]":{"size":0,"mtime_nanos":0,"mode":0,"is_dir":true},"apps/web/.next/static/chunks/pages/_error-7e26571418864af4.js":{"size":5656,"mtime_nanos":1784207314118562400,"mode":420,"is_dir":false},"apps/web/.next/server/app/tutor/lessons/page_client-reference-manifest.js":{"size":20533,"mtime_nanos":1784207314188987300,"mode":420,"is_dir":false},"apps/web/.next/server/chunks/1021.js":{"size":69179,"mtime_nanos":1784207290838229200,"mode":420,"is_dir":false},"apps/web/.next/types/app/book-lesson":{"size":0,"mtime_nanos":0,"mode":0,"is_dir":true},"apps/web/.next/static/chunks/app/tutor/earnings":{"size":0,"mtime_nanos":0,"mode":0,"is_dir":true},"apps/web/.next/server/app/auth/callback.meta":{"size":217,"mtime_nanos":1784218157408914600,"mode":420,"is_dir":false},"apps/web/.next/build-manifest.json":{"size":996,"mtime_nanos":1784207314097513600,"mode":420,"is_dir":false},"apps/web/.next/static/chunks/app/auth/callback/page-b2531b6e4746ae72.js":{"size":4669,"mtime_nanos":1784207314125739600,"mode":420,"is_dir":false},"apps/web/.next/server/app/login/page_client-reference-manifest.js":{"size":20114,"mtime_nanos":1784207314185867900,"mode":420,"is_dir":false},"apps/web/.next/server/app/en/page.js.nft.json":{"size":9969,"mtime_nanos":1784277913771607100,"mode":420,"is_dir":false},"apps/web/.next/server/app/student/lessons":{"size":0,"mtime_nanos":0,"mode":0,"is_dir":true},"apps/web/.next/server/app/student/wallet":{"size":0,"mtime_nanos":0,"mode":0,"is_dir":true},"apps/web/.next/types/app/admin/page.ts":{"size":3753,"mtime_nanos":1784207290857956900,"mode":420,"is_dir":false},"apps/web/.next/server/app/courses/[id]/page_client-reference-manifest.js":{"size":20682,"mtime_nanos":1784207314160189600,"mode":420,"is_dir":false},"apps/web/.next/server/app/login":{"size":0,"mtime_nanos":0,"mode":0,"is_dir":true},"apps/web/.next/server/app/student/discover.html":{"size":11312,"mtime_nanos":1784218157408914600,"mode":420,"is_dir":false},"apps/web/.next/server/app/admin/teachers.rsc":{"size":6355,"mtime_nanos":1784218154874627300,"mode":420,"is_dir":false},"apps/web/.next/server/app/login.html":{"size":14511,"mtime_nanos":1784218156489179900,"mode":420,"is_dir":false},"apps/web/.next/server/app/tutor/availability/page_client-reference-manifest.js":{"size":20596,"mtime_nanos":1784207314187990400,"mode":420,"is_dir":false},"apps/web/.next/static/chunks/app/student/lessons":{"size":0,"mtime_nanos":0,"mode":0,"is_dir":true},"apps/web/.next/server/app/register.rsc":{"size":5973,"mtime_nanos":1784218157408914600,"mode":420,"is_dir":false},"apps/web/.next/static/chunks/app/tutors/[id]/page-980bab2f332ab41f.js":{"size":11080,"mtime_nanos":1784207314137551000,"mode":420,"is_dir":false},"apps/web/.next/types/app/classroom/[roomId]":{"size":0,"mtime_nanos":0,"mode":0,"is_dir":true},"apps/web/.next/diagnostics":{"size":0,"mtime_nanos":0,"mode":0,"is_dir":true},"apps/web/.next/server/app/student.rsc":{"size":6065,"mtime_nanos":1784218154874627300,"mode":420,"is_dir":false},"apps/web/.next/types/app/tutor/profile/page.ts":{"size":3783,"mtime_nanos":1784207290857956900,"mode":420,"is_dir":false},"apps/web/.next/server/app/register/page.js.nft.json":{"size":9969,"mtime_nanos":1784277913771607100,"mode":420,"is_dir":false},"apps/web/.next/static/chunks/pages/_app-bcec4a5b99adb606.js":{"size":917,"mtime_nanos":1784207314107237500,"mode":420,"is_dir":false},"apps/web/.next/server/app/courses/page.js":{"size":27828,"mtime_nanos":1784207290821561600,"mode":420,"is_dir":false},"apps/web/.next/types/app/vocabulary":{"size":0,"mtime_nanos":0,"mode":0,"is_dir":true},"apps/web/.next/server/app/faq.rsc":{"size":5895,"mtime_nanos":1784218156489179900,"mode":420,"is_dir":false},"apps/web/.next/static/chunks/2919-61147c3d4ba41e63.js":{"size":13880,"mtime_nanos":1784207314154152500,"mode":420,"is_dir":false},"apps/web/.next/types/app/courses/page.ts":{"size":3759,"mtime_nanos":1784207290851895500,"mode":420,"is_dir":false},"apps/web/.next/types/app/tutor/earnings":{"size":0,"mtime_nanos":0,"mode":0,"is_dir":true},"apps/web/.next/static/chunks/app/student/wallet/page-73b2d912d8596429.js":{"size":22752,"mtime_nanos":1784207314132825800,"mode":420,"is_dir":false},"apps/web/.next/server/app/privacy/page.js":{"size":28010,"mtime_nanos":1784207290824600100,"mode":420,"is_dir":false},"apps/web/.next/static/chunks/app/help":{"size":0,"mtime_nanos":0,"mode":0,"is_dir":true},"apps/web/.next/types/app/classroom/[roomId]/page.ts":{"size":3798,"mtime_nanos":1784207290861009700,"mode":420,"is_dir":false},"apps/web/.next/server/chunks/2717.js":{"size":8913,"mtime_nanos":1784207290838229200,"mode":420,"is_dir":false},"apps/web/.next/types/cache-life.d.ts":{"size":5863,"mtime_nanos":1784207290861009700,"mode":420,"is_dir":false},"apps/web/.next/types/app/login/page.ts":{"size":3753,"mtime_nanos":1784207290851895500,"mode":420,"is_dir":false},"apps/web/.next/server/app/student/discover/page_client-reference-manifest.js":{"size":20593,"mtime_nanos":1784207314186874600,"mode":420,"is_dir":false},"apps/web/.next/server/app/become-teacher.meta":{"size":202,"mtime_nanos":1784218153561476600,"mode":420,"is_dir":false},"apps/web/.next/types/app/page.ts":{"size":3729,"mtime_nanos":1784207290859951800,"mode":420,"is_dir":false},"apps/web/.next/server/chunks/669.js":{"size":70053,"mtime_nanos":1784207290834615900,"mode":420,"is_dir":false},"apps/web/.next/static/chunks/app/admin/teachers/page-36cd5a60f68e64d8.js":{"size":17816,"mtime_nanos":1784207314125739600,"mode":420,"is_dir":false},"apps/web/.next/server/app/_not-found.meta":{"size":207,"mtime_nanos":1784218156489179900,"mode":420,"is_dir":false},"apps/web/.next/server/app/admin.meta":{"size":175,"mtime_nanos":1784218154859006900,"mode":420,"is_dir":false},"apps/web/.next/static/chunks/3936-00993f83cdfd5dd9.js":{"size":16613,"mtime_nanos":1784207314147506600,"mode":420,"is_dir":false},"apps/web/.next/server/app/auth/callback.html":{"size":10876,"mtime_nanos":1784218157408914600,"mode":420,"is_dir":false},"apps/web/.next/server/app/privacy/page_client-reference-manifest.js":{"size":20072,"mtime_nanos":1784207314185867900,"mode":420,"is_dir":false},"apps/web/.next/server/edge-runtime-webpack.js":{"size":1504,"mtime_nanos":1784207294798268200,"mode":420,"is_dir":false},"apps/web/.next/types/app/auth/callback":{"size":0,"mtime_nanos":0,"mode":0,"is_dir":true},"apps/web/.next/static/chunks/app/terms/page-31c3ed7a6a598d1d.js":{"size":11028,"mtime_nanos":1784207314134069400,"mode":420,"is_dir":false},"apps/web/.next/server/app/student":{"size":0,"mtime_nanos":0,"mode":0,"is_dir":true},"apps/web/.next/static/chunks/app/student/page-10b46fbf6266ad5e.js":{"size":62755,"mtime_nanos":1784207314141637500,"mode":420,"is_dir":false},"apps/web/.next/server/app/student/wallet/page_client-reference-manifest.js":{"size":20540,"mtime_nanos":1784207314191065800,"mode":420,"is_dir":false},"apps/web/.next/types/package.json":{"size":18,"mtime_nanos":1784207290861009700,"mode":420,"is_dir":false},"apps/web/.next/server/app/vocabulary/page_client-reference-manifest.js":{"size":20177,"mtime_nanos":1784207314190068400,"mode":420,"is_dir":false},"apps/web/.next/static/chunks/app/login":{"size":0,"mtime_nanos":0,"mode":0,"is_dir":true},"apps/web/.next/static/chunks/app/become-teacher":{"size":0,"mtime_nanos":0,"mode":0,"is_dir":true},"apps/web/.next/app-build-manifest.json":{"size":17982,"mtime_nanos":1784207314097513600,"mode":420,"is_dir":false},"apps/web/.next/server/app/student/profile.html":{"size":11307,"mtime_nanos":1784218157705722200,"mode":420,"is_dir":false},"apps/web/.next/static/chunks/app/tutor":{"size":0,"mtime_nanos":0,"mode":0,"is_dir":true},"apps/web/.next/server/app/become-teacher/page.js.nft.json":{"size":9946,"mtime_nanos":1784277913771607100,"mode":420,"is_dir":false},"apps/web/.next/types/app/student/profile/page.ts":{"size":3789,"mtime_nanos":1784207290856959900,"mode":420,"is_dir":false},"apps/web/.next/server/app/tutor/page.js":{"size":79387,"mtime_nanos":1784207290835612200,"mode":420,"is_dir":false},"apps/web/.next/server/app/tutor":{"size":0,"mtime_nanos":0,"mode":0,"is_dir":true},"apps/web/.next/next-minimal-server.js.nft.json":{"size":17979,"mtime_nanos":1784277913880955200,"mode":420,"is_dir":false},"apps/web/.next/types/app/student/discover/page.ts":{"size":3792,"mtime_nanos":1784207290856959900,"mode":420,"is_dir":false},"apps/web/.next/server/chunks/4815.js":{"size":12173,"mtime_nanos":1784207290838229200,"mode":420,"is_dir":false},"apps/web/.next/server/app/help/page.js.nft.json":{"size":9969,"mtime_nanos":1784277913771607100,"mode":420,"is_dir":false},"apps/web/.next/server/app/become-teacher":{"size":0,"mtime_nanos":0,"mode":0,"is_dir":true},"apps/web/.next/static/chunks/7589-8ddbfe2ca636f379.js":{"size":172931,"mtime_nanos":1784207314148504100,"mode":420,"is_dir":false},"apps/web/.next/server/app/courses/[id]":{"size":0,"mtime_nanos":0,"mode":0,"is_dir":true},"apps/web/.next/server/app/tutors/[id]/page.js.nft.json":{"size":10203,"mtime_nanos":1784277913771607100,"mode":420,"is_dir":false},"apps/web/.next/server/app/vocabulary/page.js":{"size":25526,"mtime_nanos":1784207290828897100,"mode":420,"is_dir":false},"apps/web/.next/server/middleware-react-loadable-manifest.js":{"size":669,"mtime_nanos":1784207314097513600,"mode":420,"is_dir":false},"apps/web/.next/static/chunks/4184-69d61be405189026.js":{"size":113637,"mtime_nanos":1784207314148504100,"mode":420,"is_dir":false},"apps/web/.next/static/chunks/app/courses/[id]/page-896b7f6951bba371.js":{"size":21385,"mtime_nanos":1784207314126736300,"mode":420,"is_dir":false},"apps/web/.next/server/app/student/wallet.rsc":{"size":6307,"mtime_nanos":1784218157408914600,"mode":420,"is_dir":false},"apps/web/.next/server/server-reference-manifest.json":{"size":84,"mtime_nanos":1784207290861009700,"mode":420,"is_dir":false},"apps/web/.next/static/chunks/app/invite/accept":{"size":0,"mtime_nanos":0,"mode":0,"is_dir":true},"apps/web/.next/types/routes.d.ts":{"size":2760,"mtime_nanos":1784207280087820900,"mode":420,"is_dir":false},"apps/web/.next/types/validator.ts":{"size":11816,"mtime_nanos":1784207280089815500,"mode":420,"is_dir":false},"apps/web/.next/server/app/terms.rsc":{"size":5913,"mtime_nanos":1784218153545855200,"mode":420,"is_dir":false},"apps/web/.next/server/middleware-manifest.json":{"size":2905,"mtime_nanos":1784207294799323800,"mode":420,"is_dir":false},"apps/web/.next/static/chunks/app/student/profile/page-4b1a4a1f7592e8b4.js":{"size":159,"mtime_nanos":1784207314132825800,"mode":420,"is_dir":false},"apps/web/.next/types/app/student/profile":{"size":0,"mtime_nanos":0,"mode":0,"is_dir":true},"apps/web/.next/static/chunks/webpack-83f67edb48951208.js":{"size":3345,"mtime_nanos":1784207314142636300,"mode":420,"is_dir":false},"apps/web/.next/static/chunks/app/admin/articles/page-123e61f875c577cc.js":{"size":13693,"mtime_nanos":1784207314124742500,"mode":420,"is_dir":false},"apps/web/.next/static/chunks/app/_not-found/page-2e854b47acae6182.js":{"size":2674,"mtime_nanos":1784207314121076500,"mode":420,"is_dir":false},"apps/web/.next/static/chunks/app/admin/payouts/page-085c688ff0cf06e9.js":{"size":198,"mtime_nanos":1784207314125739600,"mode":420,"is_dir":false},"apps/web/.next/types/app/forgot-password/page.ts":{"size":3783,"mtime_nanos":1784207290851895500,"mode":420,"is_dir":false},"apps/web/.next/types/app/terms/page.ts":{"size":3753,"mtime_nanos":1784207290856959900,"mode":420,"is_dir":false},"apps/web/.next/server/app/en.meta":{"size":166,"mtime_nanos":1784218154874627300,"mode":420,"is_dir":false},"apps/web/.next/server/app/teacher-training.html":{"size":10905,"mtime_nanos":1784218153561476600,"mode":420,"is_dir":false},"apps/web/.next/server/app-paths-manifest.json":{"size":1780,"mtime_nanos":1784207294775534700,"mode":420,"is_dir":false},"apps/web/.next/static/chunks/app/tutors":{"size":0,"mtime_nanos":0,"mode":0,"is_dir":true},"apps/web/.next/static/SCGubTP48JQlyBvub_uJC":{"size":0,"mtime_nanos":0,"mode":0,"is_dir":true},"apps/web/.next/types/app/forgot-password":{"size":0,"mtime_nanos":0,"mode":0,"is_dir":true},"apps/web/.next/server/chunks/9685.js":{"size":13829,"mtime_nanos":1784207290834615900,"mode":420,"is_dir":false},"apps/web/.next/types/app/student/wallet/page.ts":{"size":3786,"mtime_nanos":1784207290856959900,"mode":420,"is_dir":false},"apps/web/.next/server/app/student/wallet/page.js.nft.json":{"size":10112,"mtime_nanos":1784277913771607100,"mode":420,"is_dir":false},"apps/web/.next/server/pages/_error.js":{"size":79988,"mtime_nanos":1784207290818093000,"mode":420,"is_dir":false},"apps/web/.next/static/chunks/app/page-c29dc41bbc9c59d7.js":{"size":25063,"mtime_nanos":1784207314141637500,"mode":420,"is_dir":false},"apps/web/.next/types/app/teacher-training":{"size":0,"mtime_nanos":0,"mode":0,"is_dir":true},"apps/web/.next/server/app/tutors":{"size":0,"mtime_nanos":0,"mode":0,"is_dir":true},"apps/web/.next/server/app/admin/payouts/page.js.nft.json":{"size":10138,"mtime_nanos":1784277913771607100,"mode":420,"is_dir":false},"apps/web/.next/server/app/courses/[id]/page.js":{"size":34543,"mtime_nanos":1784207290821561600,"mode":420,"is_dir":false},"apps/web/.next/server/app/teacher-training":{"size":0,"mtime_nanos":0,"mode":0,"is_dir":true},"apps/web/.next/types/app/login":{"size":0,"mtime_nanos":0,"mode":0,"is_dir":true},"apps/web/.next/server/app/admin/articles":{"size":0,"mtime_nanos":0,"mode":0,"is_dir":true},"apps/web/.next/static/chunks/2078-f57d057078b54cfc.js":{"size":13829,"mtime_nanos":1784207314155149900,"mode":420,"is_dir":false},"apps/web/.next/types/app/vocabulary/page.ts":{"size":3768,"mtime_nanos":1784207290857956900,"mode":420,"is_dir":false},"apps/web/.next/static/chunks/9258-14d29effa9384e2f.js":{"size":8338,"mtime_nanos":1784207314147506600,"mode":420,"is_dir":false},"apps/web/.next/server/app/reset-password/page.js":{"size":21496,"mtime_nanos":1784207290826595200,"mode":420,"is_dir":false},"apps/web/.turbo/turbo-build.log":{"size":3942,"mtime_nanos":1784277914583912500,"mode":420,"is_dir":false},"apps/web/.next/export-marker.json":{"size":111,"mtime_nanos":1784218162867842900,"mode":420,"is_dir":false},"apps/web/.next/server/app/faq.html":{"size":21357,"mtime_nanos":1784218156489179900,"mode":420,"is_dir":false},"apps/web/.next/static/chunks/app/terms":{"size":0,"mtime_nanos":0,"mode":0,"is_dir":true},"apps/web/.next/server/app/tutor.rsc":{"size":6057,"mtime_nanos":1784218154874627300,"mode":420,"is_dir":false},"apps/web/.next/server/app/forgot-password.meta":{"size":205,"mtime_nanos":1784218156489179900,"mode":420,"is_dir":false},"apps/web/.next/server/app/admin/payouts":{"size":0,"mtime_nanos":0,"mode":0,"is_dir":true},"apps/web/.next/server/app/reset-password/page_client-reference-manifest.js":{"size":20093,"mtime_nanos":1784207314185867900,"mode":420,"is_dir":false},"apps/web/.next/server/app/terms/page.js":{"size":27937,"mtime_nanos":1784207290827806900,"mode":420,"is_dir":false},"apps/web/.next/types":{"size":0,"mtime_nanos":0,"mode":0,"is_dir":true},"apps/web/.next/types/app/courses/[id]/page.ts":{"size":3780,"mtime_nanos":1784207290852938100,"mode":420,"is_dir":false},"apps/web/.next/types/app/reset-password/page.ts":{"size":3780,"mtime_nanos":1784207290852938100,"mode":420,"is_dir":false},"apps/web/.next/server/app/en/page.js":{"size":34523,"mtime_nanos":1784207290831890000,"mode":420,"is_dir":false},"apps/web/.next/types/app/en/page.ts":{"size":3744,"mtime_nanos":1784207290857956900,"mode":420,"is_dir":false},"apps/web/.next/server/chunks/2100.js":{"size":8876,"mtime_nanos":1784207290838229200,"mode":420,"is_dir":false},"apps/web/.next/static/chunks/app/teacher-training":{"size":0,"mtime_nanos":0,"mode":0,"is_dir":true},"apps/web/.next/server/app/student/page_client-reference-manifest.js":{"size":20216,"mtime_nanos":1784207314191065800,"mode":420,"is_dir":false},"apps/web/.next/types/app/tutor":{"size":0,"mtime_nanos":0,"mode":0,"is_dir":true},"apps/web/.next/server/next-font-manifest.json":{"size":77,"mtime_nanos":1784207314097513600,"mode":420,"is_dir":false},"apps/web/.next/static/chunks/app/invite/accept/page-e215a0916857ff1b.js":{"size":6945,"mtime_nanos":1784207314129767000,"mode":420,"is_dir":false},"apps/web/.next/server/app/invite/accept.rsc":{"size":6255,"mtime_nanos":1784218157752585400,"mode":420,"is_dir":false},"apps/web/.next/server/app/tutor/earnings.meta":{"size":221,"mtime_nanos":1784218153561476600,"mode":420,"is_dir":false},"apps/web/.next/server/app/admin/page.js":{"size":101160,"mtime_nanos":1784207290830892300,"mode":420,"is_dir":false},"apps/web/.next/server/app/auth/callback":{"size":0,"mtime_nanos":0,"mode":0,"is_dir":true},"apps/web/.next/server/app/book-lesson":{"size":0,"mtime_nanos":0,"mode":0,"is_dir":true},"apps/web/.next/server/app/forgot-password/page.js":{"size":20286,"mtime_nanos":1784207290821561600,"mode":420,"is_dir":false},"apps/web/.next/static/chunks/app/teacher-training/page-2ef5070d09c24f12.js":{"size":6444,"mtime_nanos":1784207314134069400,"mode":420,"is_dir":false},"apps/web/.next/types/app/terms":{"size":0,"mtime_nanos":0,"mode":0,"is_dir":true},"apps/web/.next/types/app/invite/accept/page.ts":{"size":3783,"mtime_nanos":1784207290853935500,"mode":420,"is_dir":false},"apps/web/.next/types/app/auth":{"size":0,"mtime_nanos":0,"mode":0,"is_dir":true},"apps/web/.next/server/app/courses.html":{"size":20393,"mtime_nanos":1784218156489179900,"mode":420,"is_dir":false},"apps/web/.next/package.json":{"size":20,"mtime_nanos":1784207280107103700,"mode":420,"is_dir":false},"apps/web/.next/server/app/page.js":{"size":42210,"mtime_nanos":1784207290832886500,"mode":420,"is_dir":false},"apps/web/.next/server/chunks/282.js":{"size":140827,"mtime_nanos":1784207290837616300,"mode":420,"is_dir":false},"apps/web/.next/static/chunks/app/tutor/page-0c4f64a6f546be59.js":{"size":56277,"mtime_nanos":1784207314142636300,"mode":420,"is_dir":false},"apps/web/.next/static/chunks/app/student/lessons/page-f90851c45ef82510.js":{"size":6861,"mtime_nanos":1784207314131763500,"mode":420,"is_dir":false},"apps/web/.next/react-loadable-manifest.json":{"size":671,"mtime_nanos":1784207314097513600,"mode":420,"is_dir":false},"apps/web/.next/server/app/invite/accept.meta":{"size":219,"mtime_nanos":1784218157768208000,"mode":420,"is_dir":false},"apps/web/.next/server/app/teacher-training.meta":{"size":208,"mtime_nanos":1784218153561476600,"mode":420,"is_dir":false},"apps/web/.next/static/chunks/main-a0d7cff1b194b6ab.js":{"size":132370,"mtime_nanos":1784207314105063300,"mode":420,"is_dir":false},"apps/web/.next/static/chunks/app/student/wallet":{"size":0,"mtime_nanos":0,"mode":0,"is_dir":true},"apps/web/.next/server/app/forgot-password/page_client-reference-manifest.js":{"size":20096,"mtime_nanos":1784207314184484200,"mode":420,"is_dir":false},"apps/web/.next/server/app/student/wallet.html":{"size":14105,"mtime_nanos":1784218157408914600,"mode":420,"is_dir":false},"apps/web/.next/static/chunks/5939-f6427f0d4bbc0ab6.js":{"size":8534,"mtime_nanos":1784207314146508600,"mode":420,"is_dir":false},"apps/web/.next/static/css":{"size":0,"mtime_nanos":0,"mode":0,"is_dir":true},"apps/web/.next/server/app/help/page_client-reference-manifest.js":{"size":20062,"mtime_nanos":1784207314184484200,"mode":420,"is_dir":false},"apps/web/.next/server/app/register":{"size":0,"mtime_nanos":0,"mode":0,"is_dir":true},"apps/web/.next/types/app/tutors/[id]/page.ts":{"size":3777,"mtime_nanos":1784207290858954600,"mode":420,"is_dir":false},"apps/web/.next/server/pages/_document.js.nft.json":{"size":10231,"mtime_nanos":1784277913834057600,"mode":420,"is_dir":false},"apps/web/.next/static/chunks/app/admin/page-ed00b3dea5a5b456.js":{"size":87729,"mtime_nanos":1784207314137551000,"mode":420,"is_dir":false},"apps/web/.next/server/app/admin/teachers/page.js.nft.json":{"size":10137,"mtime_nanos":1784277913771607100,"mode":420,"is_dir":false},"apps/web/.next/server/app/tutor/lessons.html":{"size":10678,"mtime_nanos":1784218153561476600,"mode":420,"is_dir":false},"apps/web/.next/server/app/register.html":{"size":14342,"mtime_nanos":1784218157408914600,"mode":420,"is_dir":false},"apps/web/.next/server/app/admin/payouts.html":{"size":10808,"mtime_nanos":1784218156489179900,"mode":420,"is_dir":false},"apps/web/.next/server/app/reset-password.meta":{"size":202,"mtime_nanos":1784218157408914600,"mode":420,"is_dir":false},"apps/web/.next/server/app/courses.rsc":{"size":6065,"mtime_nanos":1784218156489179900,"mode":420,"is_dir":false},"apps/web/.next/server/app/tutor/availability.html":{"size":11102,"mtime_nanos":1784218153561476600,"mode":420,"is_dir":false},"apps/web/.next/server/pages/_app.js":{"size":3363,"mtime_nanos":1784207290817095800,"mode":420,"is_dir":false},"apps/web/.next/server/chunks/6433.js":{"size":92675,"mtime_nanos":1784207290835612200,"mode":420,"is_dir":false},"apps/web/.next/server/app/terms/page_client-reference-manifest.js":{"size":20066,"mtime_nanos":1784207314188987300,"mode":420,"is_dir":false},"apps/web/.next/server/app/student/discover":{"size":0,"mtime_nanos":0,"mode":0,"is_dir":true},"apps/web/.next/static/chunks/app/en/page-f0d1a5e705d1f104.js":{"size":17273,"mtime_nanos":1784207314137551000,"mode":420,"is_dir":false},"apps/web/.next/server/app/classroom":{"size":0,"mtime_nanos":0,"mode":0,"is_dir":true},"apps/web/.next/types/app/tutor/profile":{"size":0,"mtime_nanos":0,"mode":0,"is_dir":true},"apps/web/.next/server/app/favicon.ico.meta":{"size":211,"mtime_nanos":1784218155171356300,"mode":420,"is_dir":false},"apps/web/.next/server/chunks":{"size":0,"mtime_nanos":0,"mode":0,"is_dir":true},"apps/web/.next/diagnostics/framework.json":{"size":38,"mtime_nanos":1784207280109099300,"mode":420,"is_dir":false},"apps/web/.next/static/chunks/app/student/profile":{"size":0,"mtime_nanos":0,"mode":0,"is_dir":true},"apps/web/.next/server/app/tutor/earnings.html":{"size":11856,"mtime_nanos":1784218153561476600,"mode":420,"is_dir":false},"apps/web/.next/server/app/invite/accept.html":{"size":10758,"mtime_nanos":1784218157768208000,"mode":420,"is_dir":false},"apps/web/.next/static/chunks/app/student/discover/page-b6860a6b4116b30b.js":{"size":21864,"mtime_nanos":1784207314134069400,"mode":420,"is_dir":false},"apps/web/.next/server/app/admin/page.js.nft.json":{"size":9970,"mtime_nanos":1784277913771607100,"mode":420,"is_dir":false},"apps/web/.next/server/app/student/profile.rsc":{"size":6392,"mtime_nanos":1784218157705722200,"mode":420,"is_dir":false},"apps/web/.next/server/app/student.html":{"size":10559,"mtime_nanos":1784218154874627300,"mode":420,"is_dir":false},"apps/web/.next/server/app/admin/payouts/page.js":{"size":17185,"mtime_nanos":1784207290821561600,"mode":420,"is_dir":false},"apps/web/.next/static/chunks/app/courses":{"size":0,"mtime_nanos":0,"mode":0,"is_dir":true},"apps/web/.next/server/app/student/profile/page.js.nft.json":{"size":10281,"mtime_nanos":1784277913771607100,"mode":420,"is_dir":false},"apps/web/.next/trace":{"size":115833,"mtime_nanos":1784277913896564100,"mode":420,"is_dir":false},"apps/web/.next/server/app/auth/callback/page_client-reference-manifest.js":{"size":19995,"mtime_nanos":1784207314155149900,"mode":420,"is_dir":false},"apps/web/.next/server/app/student/page.js.nft.json":{"size":9992,"mtime_nanos":1784277913787193900,"mode":420,"is_dir":false},"apps/web/.next/types/app/faq":{"size":0,"mtime_nanos":0,"mode":0,"is_dir":true},"apps/web/.next/static/chunks/app/auth":{"size":0,"mtime_nanos":0,"mode":0,"is_dir":true},"apps/web/.next/server/app/page_client-reference-manifest.js":{"size":19762,"mtime_nanos":1784207314228354100,"mode":420,"is_dir":false},"apps/web/.next/server/pages/_document.js":{"size":376,"mtime_nanos":1784207290818093000,"mode":420,"is_dir":false},"apps/web/.next/static":{"size":0,"mtime_nanos":0,"mode":0,"is_dir":true},"apps/web/.next/server/app/tutor/availability.meta":{"size":233,"mtime_nanos":1784218153561476600,"mode":420,"is_dir":false},"apps/web/.next/static/chunks/app/faq":{"size":0,"mtime_nanos":0,"mode":0,"is_dir":true},"apps/web/.next/types/app/become-teacher":{"size":0,"mtime_nanos":0,"mode":0,"is_dir":true},"apps/web/.next/server/app/admin/payouts.rsc":{"size":6351,"mtime_nanos":1784218156489179900,"mode":420,"is_dir":false},"apps/web/.next/server/app/tutors/[id]":{"size":0,"mtime_nanos":0,"mode":0,"is_dir":true},"apps/web/.next/server/app/admin/payouts/page_client-reference-manifest.js":{"size":20485,"mtime_nanos":1784207314155149900,"mode":420,"is_dir":false},"apps/web/.next/server/app/privacy.meta":{"size":181,"mtime_nanos":1784218157408914600,"mode":420,"is_dir":false},"apps/web/.next/static/chunks/polyfills-42372ed130431b0a.js":{"size":112594,"mtime_nanos":1784207314103201800,"mode":420,"is_dir":false},"apps/web/.next/server/pages/404.html":{"size":10370,"mtime_nanos":1784218156489179900,"mode":420,"is_dir":false},"apps/web/.next/static/chunks/app/tutors/[id]/error-d90c0aef72025ca6.js":{"size":1765,"mtime_nanos":1784207314137551000,"mode":420,"is_dir":false},"apps/web/.next/server/app/tutor/earnings/page_client-reference-manifest.js":{"size":20584,"mtime_nanos":1784207314187990400,"mode":420,"is_dir":false},"apps/web/.next/static/chunks/2367-27bbfbe408de4241.js":{"size":14210,"mtime_nanos":1784207314148504100,"mode":420,"is_dir":false},"apps/web/.next/types/app/tutor/lessons/page.ts":{"size":3783,"mtime_nanos":1784207290857956900,"mode":420,"is_dir":false},"apps/web/.next/next-server.js.nft.json":{"size":115252,"mtime_nanos":1784277913880955200,"mode":420,"is_dir":false},"apps/web/.next/static/chunks/app/admin/teachers":{"size":0,"mtime_nanos":0,"mode":0,"is_dir":true},"apps/web/.next/static/chunks/app/student/discover":{"size":0,"mtime_nanos":0,"mode":0,"is_dir":true},"apps/web/.next/server/app/admin/articles/page.js.nft.json":{"size":10162,"mtime_nanos":1784277913771607100,"mode":420,"is_dir":false},"apps/web/.next/server/app/tutor/profile.html":{"size":11295,"mtime_nanos":1784218154859006900,"mode":420,"is_dir":false},"apps/web/.next/server/app/en.html":{"size":27927,"mtime_nanos":1784218154874627300,"mode":420,"is_dir":false},"apps/web/.next/server/app/teacher-training.rsc":{"size":6053,"mtime_nanos":1784218153561476600,"mode":420,"is_dir":false},"apps/web/.next/server/server-reference-manifest.js":{"size":123,"mtime_nanos":1784207290861009700,"mode":420,"is_dir":false},"apps/web/.next/static/chunks/app/tutors/[id]":{"size":0,"mtime_nanos":0,"mode":0,"is_dir":true},"apps/web/.next/server/app/teacher-training/page.js":{"size":21911,"mtime_nanos":1784207290827592600,"mode":420,"is_dir":false},"apps/web/.next/server/app/reset-password.html":{"size":13296,"mtime_nanos":1784218157487021000,"mode":420,"is_dir":false},"apps/web/.next/server/app/admin/articles.html":{"size":12816,"mtime_nanos":1784218154874627300,"mode":420,"is_dir":false},"apps/web/.next/server/app/book-lesson/page.js.nft.json":{"size":9969,"mtime_nanos":1784277913771607100,"mode":420,"is_dir":false},"apps/web/.next/server/src/middleware.js.map":{"size":396718,"mtime_nanos":1784207294800321600,"mode":420,"is_dir":false},"apps/web/.next/server/src":{"size":0,"mtime_nanos":0,"mode":0,"is_dir":true},"apps/web/.next/static/SCGubTP48JQlyBvub_uJC/_buildManifest.js":{"size":1866,"mtime_nanos":1784207314105063300,"mode":420,"is_dir":false},"apps/web/.next/server/app/help.html":{"size":20332,"mtime_nanos":1784218157408914600,"mode":420,"is_dir":false},"apps/web/.next/server/app/login/page.js.nft.json":{"size":9969,"mtime_nanos":1784277913771607100,"mode":420,"is_dir":false},"apps/web/.next/server/app/privacy/page.js.nft.json":{"size":9969,"mtime_nanos":1784277913771607100,"mode":420,"is_dir":false},"apps/web/.next/prerender-manifest.json":{"size":20928,"mtime_nanos":1784218162513716000,"mode":420,"is_dir":false},"apps/web/.next/static/chunks/app/en":{"size":0,"mtime_nanos":0,"mode":0,"is_dir":true},"apps/web/.next":{"size":0,"mtime_nanos":0,"mode":0,"is_dir":true},"apps/web/.next/server/app/admin/teachers.meta":{"size":221,"mtime_nanos":1784218154874627300,"mode":420,"is_dir":false},"apps/web/.next/types/app/student/lessons":{"size":0,"mtime_nanos":0,"mode":0,"is_dir":true},"apps/web/.next/server/app/book-lesson/page.js":{"size":39990,"mtime_nanos":1784207290832886500,"mode":420,"is_dir":false},"apps/web/.next/server/app/tutor/availability":{"size":0,"mtime_nanos":0,"mode":0,"is_dir":true},"apps/web/.next/server/app/faq.meta":{"size":169,"mtime_nanos":1784218156489179900,"mode":420,"is_dir":false},"apps/web/.next/server/app/invite/accept/page.js":{"size":22342,"mtime_nanos":1784207290826595200,"mode":420,"is_dir":false}},"order":["apps/web/.next","apps/web/.next/BUILD_ID","apps/web/.next/app-build-manifest.json","apps/web/.next/app-path-routes-manifest.json","apps/web/.next/build-manifest.json","apps/web/.next/diagnostics","apps/web/.next/diagnostics/build-diagnostics.json","apps/web/.next/diagnostics/framework.json","apps/web/.next/export-marker.json","apps/web/.next/images-manifest.json","apps/web/.next/next-minimal-server.js.nft.json","apps/web/.next/next-server.js.nft.json","apps/web/.next/package.json","apps/web/.next/prerender-manifest.json","apps/web/.next/react-loadable-manifest.json","apps/web/.next/required-server-files.json","apps/web/.next/routes-manifest.json","apps/web/.next/server","apps/web/.next/server/app","apps/web/.next/server/app/_not-found","apps/web/.next/server/app/_not-found/page.js","apps/web/.next/server/app/_not-found/page.js.nft.json","apps/web/.next/server/app/_not-found/page_client-reference-manifest.js","apps/web/.next/server/app/_not-found.html","apps/web/.next/server/app/_not-found.meta","apps/web/.next/server/app/_not-found.rsc","apps/web/.next/server/app/admin","apps/web/.next/server/app/admin/articles","apps/web/.next/server/app/admin/articles/page.js","apps/web/.next/server/app/admin/articles/page.js.nft.json","apps/web/.next/server/app/admin/articles/page_client-reference-manifest.js","apps/web/.next/server/app/admin/articles.html","apps/web/.next/server/app/admin/articles.meta","apps/web/.next/server/app/admin/articles.rsc","apps/web/.next/server/app/admin/page.js","apps/web/.next/server/app/admin/page.js.nft.json","apps/web/.next/server/app/admin/page_client-reference-manifest.js","apps/web/.next/server/app/admin/payouts","apps/web/.next/server/app/admin/payouts/page.js","apps/web/.next/server/app/admin/payouts/page.js.nft.json","apps/web/.next/server/app/admin/payouts/page_client-reference-manifest.js","apps/web/.next/server/app/admin/payouts.html","apps/web/.next/server/app/admin/payouts.meta","apps/web/.next/server/app/admin/payouts.rsc","apps/web/.next/server/app/admin/teachers","apps/web/.next/server/app/admin/teachers/page.js","apps/web/.next/server/app/admin/teachers/page.js.nft.json","apps/web/.next/server/app/admin/teachers/page_client-reference-manifest.js","apps/web/.next/server/app/admin/teachers.html","apps/web/.next/server/app/admin/teachers.meta","apps/web/.next/server/app/admin/teachers.rsc","apps/web/.next/server/app/admin.html","apps/web/.next/server/app/admin.meta","apps/web/.next/server/app/admin.rsc","apps/web/.next/server/app/auth","apps/web/.next/server/app/auth/callback","apps/web/.next/server/app/auth/callback/page.js","apps/web/.next/server/app/auth/callback/page.js.nft.json","apps/web/.next/server/app/auth/callback/page_client-reference-manifest.js","apps/web/.next/server/app/auth/callback.html","apps/web/.next/server/app/auth/callback.meta","apps/web/.next/server/app/auth/callback.rsc","apps/web/.next/server/app/become-teacher","apps/web/.next/server/app/become-teacher/page.js","apps/web/.next/server/app/become-teacher/page.js.nft.json","apps/web/.next/server/app/become-teacher/page_client-reference-manifest.js","apps/web/.next/server/app/become-teacher.html","apps/web/.next/server/app/become-teacher.meta","apps/web/.next/server/app/become-teacher.rsc","apps/web/.next/server/app/book-lesson","apps/web/.next/server/app/book-lesson/page.js","apps/web/.next/server/app/book-lesson/page.js.nft.json","apps/web/.next/server/app/book-lesson/page_client-reference-manifest.js","apps/web/.next/server/app/book-lesson.html","apps/web/.next/server/app/book-lesson.meta","apps/web/.next/server/app/book-lesson.rsc","apps/web/.next/server/app/classroom","apps/web/.next/server/app/classroom/[roomId]","apps/web/.next/server/app/classroom/[roomId]/page.js","apps/web/.next/server/app/classroom/[roomId]/page.js.nft.json","apps/web/.next/server/app/classroom/[roomId]/page_client-reference-manifest.js","apps/web/.next/server/app/courses","apps/web/.next/server/app/courses/[id]","apps/web/.next/server/app/courses/[id]/page.js","apps/web/.next/server/app/courses/[id]/page.js.nft.json","apps/web/.next/server/app/courses/[id]/page_client-reference-manifest.js","apps/web/.next/server/app/courses/page.js","apps/web/.next/server/app/courses/page.js.nft.json","apps/web/.next/server/app/courses/page_client-reference-manifest.js","apps/web/.next/server/app/courses.html","apps/web/.next/server/app/courses.meta","apps/web/.next/server/app/courses.rsc","apps/web/.next/server/app/en","apps/web/.next/server/app/en/page.js","apps/web/.next/server/app/en/page.js.nft.json","apps/web/.next/server/app/en/page_client-reference-manifest.js","apps/web/.next/server/app/en.html","apps/web/.next/server/app/en.meta","apps/web/.next/server/app/en.rsc","apps/web/.next/server/app/faq","apps/web/.next/server/app/faq/page.js","apps/web/.next/server/app/faq/page.js.nft.json","apps/web/.next/server/app/faq/page_client-reference-manifest.js","apps/web/.next/server/app/faq.html","apps/web/.next/server/app/faq.meta","apps/web/.next/server/app/faq.rsc","apps/web/.next/server/app/favicon.ico","apps/web/.next/server/app/favicon.ico/route.js","apps/web/.next/server/app/favicon.ico/route.js.nft.json","apps/web/.next/server/app/favicon.ico.body","apps/web/.next/server/app/favicon.ico.meta","apps/web/.next/server/app/forgot-password","apps/web/.next/server/app/forgot-password/page.js","apps/web/.next/server/app/forgot-password/page.js.nft.json","apps/web/.next/server/app/forgot-password/page_client-reference-manifest.js","apps/web/.next/server/app/forgot-password.html","apps/web/.next/server/app/forgot-password.meta","apps/web/.next/server/app/forgot-password.rsc","apps/web/.next/server/app/help","apps/web/.next/server/app/help/page.js","apps/web/.next/server/app/help/page.js.nft.json","apps/web/.next/server/app/help/page_client-reference-manifest.js","apps/web/.next/server/app/help.html","apps/web/.next/server/app/help.meta","apps/web/.next/server/app/help.rsc","apps/web/.next/server/app/index.html","apps/web/.next/server/app/index.meta","apps/web/.next/server/app/index.rsc","apps/web/.next/server/app/invite","apps/web/.next/server/app/invite/accept","apps/web/.next/server/app/invite/accept/page.js","apps/web/.next/server/app/invite/accept/page.js.nft.json","apps/web/.next/server/app/invite/accept/page_client-reference-manifest.js","apps/web/.next/server/app/invite/accept.html","apps/web/.next/server/app/invite/accept.meta","apps/web/.next/server/app/invite/accept.rsc","apps/web/.next/server/app/login","apps/web/.next/server/app/login/page.js","apps/web/.next/server/app/login/page.js.nft.json","apps/web/.next/server/app/login/page_client-reference-manifest.js","apps/web/.next/server/app/login.html","apps/web/.next/server/app/login.meta","apps/web/.next/server/app/login.rsc","apps/web/.next/server/app/page.js","apps/web/.next/server/app/page.js.nft.json","apps/web/.next/server/app/page_client-reference-manifest.js","apps/web/.next/server/app/privacy","apps/web/.next/server/app/privacy/page.js","apps/web/.next/server/app/privacy/page.js.nft.json","apps/web/.next/server/app/privacy/page_client-reference-manifest.js","apps/web/.next/server/app/privacy.html","apps/web/.next/server/app/privacy.meta","apps/web/.next/server/app/privacy.rsc","apps/web/.next/server/app/register","apps/web/.next/server/app/register/page.js","apps/web/.next/server/app/register/page.js.nft.json","apps/web/.next/server/app/register/page_client-reference-manifest.js","apps/web/.next/server/app/register.html","apps/web/.next/server/app/register.meta","apps/web/.next/server/app/register.rsc","apps/web/.next/server/app/reset-password","apps/web/.next/server/app/reset-password/page.js","apps/web/.next/server/app/reset-password/page.js.nft.json","apps/web/.next/server/app/reset-password/page_client-reference-manifest.js","apps/web/.next/server/app/reset-password.html","apps/web/.next/server/app/reset-password.meta","apps/web/.next/server/app/reset-password.rsc","apps/web/.next/server/app/student","apps/web/.next/server/app/student/discover","apps/web/.next/server/app/student/discover/page.js","apps/web/.next/server/app/student/discover/page.js.nft.json","apps/web/.next/server/app/student/discover/page_client-reference-manifest.js","apps/web/.next/server/app/student/discover.html","apps/web/.next/server/app/student/discover.meta","apps/web/.next/server/app/student/discover.rsc","apps/web/.next/server/app/student/lessons","apps/web/.next/server/app/student/lessons/page.js","apps/web/.next/server/app/student/lessons/page.js.nft.json","apps/web/.next/server/app/student/lessons/page_client-reference-manifest.js","apps/web/.next/server/app/student/lessons.html","apps/web/.next/server/app/student/lessons.meta","apps/web/.next/server/app/student/lessons.rsc","apps/web/.next/server/app/student/page.js","apps/web/.next/server/app/student/page.js.nft.json","apps/web/.next/server/app/student/page_client-reference-manifest.js","apps/web/.next/server/app/student/profile","apps/web/.next/server/app/student/profile/page.js","apps/web/.next/server/app/student/profile/page.js.nft.json","apps/web/.next/server/app/student/profile/page_client-reference-manifest.js","apps/web/.next/server/app/student/profile.html","apps/web/.next/server/app/student/profile.meta","apps/web/.next/server/app/student/profile.rsc","apps/web/.next/server/app/student/wallet","apps/web/.next/server/app/student/wallet/page.js","apps/web/.next/server/app/student/wallet/page.js.nft.json","apps/web/.next/server/app/student/wallet/page_client-reference-manifest.js","apps/web/.next/server/app/student/wallet.html","apps/web/.next/server/app/student/wallet.meta","apps/web/.next/server/app/student/wallet.rsc","apps/web/.next/server/app/student.html","apps/web/.next/server/app/student.meta","apps/web/.next/server/app/student.rsc","apps/web/.next/server/app/teacher-training","apps/web/.next/server/app/teacher-training/page.js","apps/web/.next/server/app/teacher-training/page.js.nft.json","apps/web/.next/server/app/teacher-training/page_client-reference-manifest.js","apps/web/.next/server/app/teacher-training.html","apps/web/.next/server/app/teacher-training.meta","apps/web/.next/server/app/teacher-training.rsc","apps/web/.next/server/app/terms","apps/web/.next/server/app/terms/page.js","apps/web/.next/server/app/terms/page.js.nft.json","apps/web/.next/server/app/terms/page_client-reference-manifest.js","apps/web/.next/server/app/terms.html","apps/web/.next/server/app/terms.meta","apps/web/.next/server/app/terms.rsc","apps/web/.next/server/app/tutor","apps/web/.next/server/app/tutor/availability","apps/web/.next/server/app/tutor/availability/page.js","apps/web/.next/server/app/tutor/availability/page.js.nft.json","apps/web/.next/server/app/tutor/availability/page_client-reference-manifest.js","apps/web/.next/server/app/tutor/availability.html","apps/web/.next/server/app/tutor/availability.meta","apps/web/.next/server/app/tutor/availability.rsc","apps/web/.next/server/app/tutor/earnings","apps/web/.next/server/app/tutor/earnings/page.js","apps/web/.next/server/app/tutor/earnings/page.js.nft.json","apps/web/.next/server/app/tutor/earnings/page_client-reference-manifest.js","apps/web/.next/server/app/tutor/earnings.html","apps/web/.next/server/app/tutor/earnings.meta","apps/web/.next/server/app/tutor/earnings.rsc","apps/web/.next/server/app/tutor/lessons","apps/web/.next/server/app/tutor/lessons/page.js","apps/web/.next/server/app/tutor/lessons/page.js.nft.json","apps/web/.next/server/app/tutor/lessons/page_client-reference-manifest.js","apps/web/.next/server/app/tutor/lessons.html","apps/web/.next/server/app/tutor/lessons.meta","apps/web/.next/server/app/tutor/lessons.rsc","apps/web/.next/server/app/tutor/page.js","apps/web/.next/server/app/tutor/page.js.nft.json","apps/web/.next/server/app/tutor/page_client-reference-manifest.js","apps/web/.next/server/app/tutor/profile","apps/web/.next/server/app/tutor/profile/page.js","apps/web/.next/server/app/tutor/profile/page.js.nft.json","apps/web/.next/server/app/tutor/profile/page_client-reference-manifest.js","apps/web/.next/server/app/tutor/profile.html","apps/web/.next/server/app/tutor/profile.meta","apps/web/.next/server/app/tutor/profile.rsc","apps/web/.next/server/app/tutor.html","apps/web/.next/server/app/tutor.meta","apps/web/.next/server/app/tutor.rsc","apps/web/.next/server/app/tutors","apps/web/.next/server/app/tutors/[id]","apps/web/.next/server/app/tutors/[id]/page.js","apps/web/.next/server/app/tutors/[id]/page.js.nft.json","apps/web/.next/server/app/tutors/[id]/page_client-reference-manifest.js","apps/web/.next/server/app/vocabulary","apps/web/.next/server/app/vocabulary/page.js","apps/web/.next/server/app/vocabulary/page.js.nft.json","apps/web/.next/server/app/vocabulary/page_client-reference-manifest.js","apps/web/.next/server/app/vocabulary.html","apps/web/.next/server/app/vocabulary.meta","apps/web/.next/server/app/vocabulary.rsc","apps/web/.next/server/app-paths-manifest.json","apps/web/.next/server/chunks","apps/web/.next/server/chunks/1021.js","apps/web/.next/server/chunks/2100.js","apps/web/.next/server/chunks/2717.js","apps/web/.next/server/chunks/282.js","apps/web/.next/server/chunks/3735.js","apps/web/.next/server/chunks/4815.js","apps/web/.next/server/chunks/6433.js","apps/web/.next/server/chunks/669.js","apps/web/.next/server/chunks/6857.js","apps/web/.next/server/chunks/7842.js","apps/web/.next/server/chunks/853.js","apps/web/.next/server/chunks/9685.js","apps/web/.next/server/edge-runtime-webpack.js","apps/web/.next/server/edge-runtime-webpack.js.map","apps/web/.next/server/functions-config-manifest.json","apps/web/.next/server/interception-route-rewrite-manifest.js","apps/web/.next/server/middleware-build-manifest.js","apps/web/.next/server/middleware-manifest.json","apps/web/.next/server/middleware-react-loadable-manifest.js","apps/web/.next/server/next-font-manifest.js","apps/web/.next/server/next-font-manifest.json","apps/web/.next/server/pages","apps/web/.next/server/pages/404.html","apps/web/.next/server/pages/500.html","apps/web/.next/server/pages/_app.js","apps/web/.next/server/pages/_app.js.nft.json","apps/web/.next/server/pages/_document.js","apps/web/.next/server/pages/_document.js.nft.json","apps/web/.next/server/pages/_error.js","apps/web/.next/server/pages/_error.js.nft.json","apps/web/.next/server/pages-manifest.json","apps/web/.next/server/server-reference-manifest.js","apps/web/.next/server/server-reference-manifest.json","apps/web/.next/server/src","apps/web/.next/server/src/middleware.js","apps/web/.next/server/src/middleware.js.map","apps/web/.next/server/webpack-runtime.js","apps/web/.next/static","apps/web/.next/static/SCGubTP48JQlyBvub_uJC","apps/web/.next/static/SCGubTP48JQlyBvub_uJC/_buildManifest.js","apps/web/.next/static/SCGubTP48JQlyBvub_uJC/_ssgManifest.js","apps/web/.next/static/chunks","apps/web/.next/static/chunks/1530-21e3e33019716615.js","apps/web/.next/static/chunks/2078-f57d057078b54cfc.js","apps/web/.next/static/chunks/2367-27bbfbe408de4241.js","apps/web/.next/static/chunks/2790-b69afaa8b092dc71.js","apps/web/.next/static/chunks/2919-61147c3d4ba41e63.js","apps/web/.next/static/chunks/2df137e7-44c7df29a0367194.js","apps/web/.next/static/chunks/3809.45b47c674c9d395c.js","apps/web/.next/static/chunks/3936-00993f83cdfd5dd9.js","apps/web/.next/static/chunks/4184-69d61be405189026.js","apps/web/.next/static/chunks/5070-e95f686c39c4cca0.js","apps/web/.next/static/chunks/5695-d695ed8825add7dd.js","apps/web/.next/static/chunks/5939-f6427f0d4bbc0ab6.js","apps/web/.next/static/chunks/7589-8ddbfe2ca636f379.js","apps/web/.next/static/chunks/7628.de6487a09aba5d83.js","apps/web/.next/static/chunks/8883-57748f83d541529e.js","apps/web/.next/static/chunks/9258-14d29effa9384e2f.js","apps/web/.next/static/chunks/app","apps/web/.next/static/chunks/app/_not-found","apps/web/.next/static/chunks/app/_not-found/page-2e854b47acae6182.js","apps/web/.next/static/chunks/app/admin","apps/web/.next/static/chunks/app/admin/articles","apps/web/.next/static/chunks/app/admin/articles/page-123e61f875c577cc.js","apps/web/.next/static/chunks/app/admin/page-ed00b3dea5a5b456.js","apps/web/.next/static/chunks/app/admin/payouts","apps/web/.next/static/chunks/app/admin/payouts/page-085c688ff0cf06e9.js","apps/web/.next/static/chunks/app/admin/teachers","apps/web/.next/static/chunks/app/admin/teachers/page-36cd5a60f68e64d8.js","apps/web/.next/static/chunks/app/auth","apps/web/.next/static/chunks/app/auth/callback","apps/web/.next/static/chunks/app/auth/callback/page-b2531b6e4746ae72.js","apps/web/.next/static/chunks/app/become-teacher","apps/web/.next/static/chunks/app/become-teacher/page-babf3191a17502ba.js","apps/web/.next/static/chunks/app/book-lesson","apps/web/.next/static/chunks/app/book-lesson/page-4feca50565b8f664.js","apps/web/.next/static/chunks/app/classroom","apps/web/.next/static/chunks/app/classroom/[roomId]","apps/web/.next/static/chunks/app/classroom/[roomId]/page-830b72951f467b42.js","apps/web/.next/static/chunks/app/courses","apps/web/.next/static/chunks/app/courses/[id]","apps/web/.next/static/chunks/app/courses/[id]/page-896b7f6951bba371.js","apps/web/.next/static/chunks/app/courses/page-e6d8beaf05128792.js","apps/web/.next/static/chunks/app/en","apps/web/.next/static/chunks/app/en/page-f0d1a5e705d1f104.js","apps/web/.next/static/chunks/app/faq","apps/web/.next/static/chunks/app/faq/page-37e353b20b648d6e.js","apps/web/.next/static/chunks/app/forgot-password","apps/web/.next/static/chunks/app/forgot-password/page-c8f9cf76c0362b01.js","apps/web/.next/static/chunks/app/help","apps/web/.next/static/chunks/app/help/page-be24dfe6cefbf80a.js","apps/web/.next/static/chunks/app/invite","apps/web/.next/static/chunks/app/invite/accept","apps/web/.next/static/chunks/app/invite/accept/page-e215a0916857ff1b.js","apps/web/.next/static/chunks/app/layout-afa5e9c4e0dde710.js","apps/web/.next/static/chunks/app/login","apps/web/.next/static/chunks/app/login/page-d873f30c2be18a89.js","apps/web/.next/static/chunks/app/page-c29dc41bbc9c59d7.js","apps/web/.next/static/chunks/app/privacy","apps/web/.next/static/chunks/app/privacy/page-09b2956fcd336986.js","apps/web/.next/static/chunks/app/register","apps/web/.next/static/chunks/app/register/page-6da29e7306a1042e.js","apps/web/.next/static/chunks/app/reset-password","apps/web/.next/static/chunks/app/reset-password/page-05d1a44a517cddcd.js","apps/web/.next/static/chunks/app/student","apps/web/.next/static/chunks/app/student/discover","apps/web/.next/static/chunks/app/student/discover/page-b6860a6b4116b30b.js","apps/web/.next/static/chunks/app/student/lessons","apps/web/.next/static/chunks/app/student/lessons/page-f90851c45ef82510.js","apps/web/.next/static/chunks/app/student/page-10b46fbf6266ad5e.js","apps/web/.next/static/chunks/app/student/profile","apps/web/.next/static/chunks/app/student/profile/page-4b1a4a1f7592e8b4.js","apps/web/.next/static/chunks/app/student/wallet","apps/web/.next/static/chunks/app/student/wallet/page-73b2d912d8596429.js","apps/web/.next/static/chunks/app/teacher-training","apps/web/.next/static/chunks/app/teacher-training/page-2ef5070d09c24f12.js","apps/web/.next/static/chunks/app/terms","apps/web/.next/static/chunks/app/terms/page-31c3ed7a6a598d1d.js","apps/web/.next/static/chunks/app/tutor","apps/web/.next/static/chunks/app/tutor/availability","apps/web/.next/static/chunks/app/tutor/availability/page-98746f615833b1be.js","apps/web/.next/static/chunks/app/tutor/earnings","apps/web/.next/static/chunks/app/tutor/earnings/page-34b60f242fbab6ad.js","apps/web/.next/static/chunks/app/tutor/lessons","apps/web/.next/static/chunks/app/tutor/lessons/page-05f203a5f76c1f44.js","apps/web/.next/static/chunks/app/tutor/page-0c4f64a6f546be59.js","apps/web/.next/static/chunks/app/tutor/profile","apps/web/.next/static/chunks/app/tutor/profile/page-5d8185e9e81c0962.js","apps/web/.next/static/chunks/app/tutors","apps/web/.next/static/chunks/app/tutors/[id]","apps/web/.next/static/chunks/app/tutors/[id]/error-d90c0aef72025ca6.js","apps/web/.next/static/chunks/app/tutors/[id]/page-980bab2f332ab41f.js","apps/web/.next/static/chunks/app/vocabulary","apps/web/.next/static/chunks/app/vocabulary/page-fe378d833b74df85.js","apps/web/.next/static/chunks/framework-d89a50f3a2bac6a1.js","apps/web/.next/static/chunks/main-a0d7cff1b194b6ab.js","apps/web/.next/static/chunks/main-app-4c5c8b63f655479c.js","apps/web/.next/static/chunks/pages","apps/web/.next/static/chunks/pages/_app-bcec4a5b99adb606.js","apps/web/.next/static/chunks/pages/_error-7e26571418864af4.js","apps/web/.next/static/chunks/polyfills-42372ed130431b0a.js","apps/web/.next/static/chunks/webpack-83f67edb48951208.js","apps/web/.next/static/css","apps/web/.next/static/css/e34b5a27d547b7a3.css","apps/web/.next/trace","apps/web/.next/types","apps/web/.next/types/app","apps/web/.next/types/app/admin","apps/web/.next/types/app/admin/articles","apps/web/.next/types/app/admin/articles/page.ts","apps/web/.next/types/app/admin/page.ts","apps/web/.next/types/app/admin/payouts","apps/web/.next/types/app/admin/payouts/page.ts","apps/web/.next/types/app/admin/teachers","apps/web/.next/types/app/admin/teachers/page.ts","apps/web/.next/types/app/auth","apps/web/.next/types/app/auth/callback","apps/web/.next/types/app/auth/callback/page.ts","apps/web/.next/types/app/become-teacher","apps/web/.next/types/app/become-teacher/page.ts","apps/web/.next/types/app/book-lesson","apps/web/.next/types/app/book-lesson/page.ts","apps/web/.next/types/app/classroom","apps/web/.next/types/app/classroom/[roomId]","apps/web/.next/types/app/classroom/[roomId]/page.ts","apps/web/.next/types/app/courses","apps/web/.next/types/app/courses/[id]","apps/web/.next/types/app/courses/[id]/page.ts","apps/web/.next/types/app/courses/page.ts","apps/web/.next/types/app/en","apps/web/.next/types/app/en/page.ts","apps/web/.next/types/app/faq","apps/web/.next/types/app/faq/page.ts","apps/web/.next/types/app/forgot-password","apps/web/.next/types/app/forgot-password/page.ts","apps/web/.next/types/app/help","apps/web/.next/types/app/help/page.ts","apps/web/.next/types/app/invite","apps/web/.next/types/app/invite/accept","apps/web/.next/types/app/invite/accept/page.ts","apps/web/.next/types/app/login","apps/web/.next/types/app/login/page.ts","apps/web/.next/types/app/page.ts","apps/web/.next/types/app/privacy","apps/web/.next/types/app/privacy/page.ts","apps/web/.next/types/app/register","apps/web/.next/types/app/register/page.ts","apps/web/.next/types/app/reset-password","apps/web/.next/types/app/reset-password/page.ts","apps/web/.next/types/app/student","apps/web/.next/types/app/student/discover","apps/web/.next/types/app/student/discover/page.ts","apps/web/.next/types/app/student/lessons","apps/web/.next/types/app/student/lessons/page.ts","apps/web/.next/types/app/student/page.ts","apps/web/.next/types/app/student/profile","apps/web/.next/types/app/student/profile/page.ts","apps/web/.next/types/app/student/wallet","apps/web/.next/types/app/student/wallet/page.ts","apps/web/.next/types/app/teacher-training","apps/web/.next/types/app/teacher-training/page.ts","apps/web/.next/types/app/terms","apps/web/.next/types/app/terms/page.ts","apps/web/.next/types/app/tutor","apps/web/.next/types/app/tutor/availability","apps/web/.next/types/app/tutor/availability/page.ts","apps/web/.next/types/app/tutor/earnings","apps/web/.next/types/app/tutor/earnings/page.ts","apps/web/.next/types/app/tutor/lessons","apps/web/.next/types/app/tutor/lessons/page.ts","apps/web/.next/types/app/tutor/page.ts","apps/web/.next/types/app/tutor/profile","apps/web/.next/types/app/tutor/profile/page.ts","apps/web/.next/types/app/tutors","apps/web/.next/types/app/tutors/[id]","apps/web/.next/types/app/tutors/[id]/page.ts","apps/web/.next/types/app/vocabulary","apps/web/.next/types/app/vocabulary/page.ts","apps/web/.next/types/cache-life.d.ts","apps/web/.next/types/package.json","apps/web/.next/types/routes.d.ts","apps/web/.next/types/validator.ts","apps/web/.turbo/turbo-build.log"]}